setup.py
rig_cpp_key_allocation/__init__.py
rig_cpp_key_allocation/cffi_compile.py
rig_cpp_key_allocation/constraints_graph.cpp
rig_cpp_key_allocation/constraints_graph.h
rig_cpp_key_allocation/version.py
rig_cpp_key_allocation.egg-info/PKG-INFO
rig_cpp_key_allocation.egg-info/SOURCES.txt
rig_cpp_key_allocation.egg-info/dependency_links.txt
rig_cpp_key_allocation.egg-info/requires.txt
rig_cpp_key_allocation.egg-info/top_level.txt