Metadata-Version: 1.1
Name: rig-cpp-key-allocation
Version: 0.1.0
Summary: A C++ library (and CFFI Python interface) for allocating SpiNNaker multicast keys.
Home-page: https://github.com/project-rig/rig_cpp_key_allocation
Author: The Rig Authors
Author-email: UNKNOWN
License: GPLv2
Keywords: spinnaker cffi graph-coloring
Platform: UNKNOWN
Classifier: Development Status :: 3 - Alpha
Classifier: Intended Audience :: Developers
Classifier: Intended Audience :: Science/Research
Classifier: License :: OSI Approved :: GNU General Public License v2 (GPLv2)
Classifier: Operating System :: POSIX :: Linux
Classifier: Operating System :: Microsoft :: Windows
Classifier: Operating System :: MacOS
Classifier: Programming Language :: Python :: 2
Classifier: Programming Language :: Python :: 2.7
Classifier: Programming Language :: Python :: 3
Classifier: Programming Language :: Python :: 3.4
Classifier: Programming Language :: Python :: 3.5
Classifier: Programming Language :: Python :: 3.6
Classifier: Topic :: Software Development :: Libraries
